[{"idDapAn":"fdf","fk_idde":"67454","fk_idThuMuc":"tm1","sDapAn":"C\/D\/C\/A\/D\/B\/A\/B\/A\/D\/A\/B\/D\/A\/C\/C\/C\/A\/A\/D\/C\/B\/C\/D\/B\/C\/C\/C\/B\/C\/A\/C\/B\/C\/D\/B\/B\/C\/A\/C","sMaCauHoi":"CH01\/CH02\/CH03\/CH04\/CH05\/CH06\/CH07\/CH08\/CH09\/CH10\/CH11\/CH12\/CH13\/CH14\/CH15\/CH16\/CH17\/CH18\/CH19\/CH20\/CH21\/CH22\/CH23\/CH24\/CH25\/CH26\/CH27\/CH28\/CH29\/CH30\/CH31\/CH32\/CH33\/CH34\/CH35\/CH36\/CH37\/CH38\/CH39\/CH40","iSoLuongCau":40,"sCLO":"1.1\/1.2\/1.3\/1.4\/1.5\/1.6\/1.7-2.1\/2.2\/2.3\/2.4\/2.5\/2.6\/2.7\/2.8\/2.9-3.1\/3.2\/3.3\/3.4\/3.5\/3.6\/3.7\/3.8-4.1\/4.2\/4.3\/4.4\/4.5\/4.6\/4.7\/4.8\/4.9\/4.10-5.1\/5.2\/5.3\/5.4\/5.5\/5.6"}]